safir/arq/__init__.py
safir/arq/_config.py
safir/arq/_exceptions.py
safir/arq/_models.py
safir/arq/_queue.py
safir/arq/py.typed
safir/arq/uws.py
safir_arq-14.2.0.dist-info/licenses/LICENSE
safir_arq-14.2.0.dist-info/METADATA
safir_arq-14.2.0.dist-info/WHEEL
safir_arq-14.2.0.dist-info/top_level.txt
safir_arq-14.2.0.dist-info/RECORD
